executor/__init__.py
executor/exception_handler.py
executor/exceptions.py
executor/executor.py
executor/runner.py
executor/utils.py
connect_reports_runner-30.0.dist-info/LICENSE
connect_reports_runner-30.0.dist-info/METADATA
connect_reports_runner-30.0.dist-info/WHEEL
connect_reports_runner-30.0.dist-info/entry_points.txt
connect_reports_runner-30.0.dist-info/RECORD
