Metadata-Version: 2.1
Name: connect-reports-runner
Version: 30.0
Summary: Connect Reports Runner
Home-page: https://connect.cloudblue.com
License: Apache-2.0
Keywords: utility,connect,cloudblue,reports
Author: CloudBlue LLC
Requires-Python: >=3.8,<4
Classifier: Development Status :: 5 - Production/Stable
Classifier: Intended Audience :: Developers
Classifier: License :: OSI Approved :: Apache Software License
Classifier: Operating System :: OS Independent
Classifier: Programming Language :: Python :: 3
Classifier: Programming Language :: Python :: 3.8
Classifier: Programming Language :: Python :: 3.9
Classifier: Programming Language :: Python :: 3.10
Classifier: Programming Language :: Python :: 3.11
Classifier: Programming Language :: Python :: 3.12
Classifier: Topic :: Software Development :: Libraries
Classifier: Topic :: Utilities
Requires-Dist: chardet (==3.*)
Requires-Dist: connect-openapi-client (>=25.4)
Requires-Dist: connect-reports-core (==26.*)
Requires-Dist: lxml (==4.*)
Requires-Dist: openpyxl (==3.*)
Requires-Dist: requests (==2.*)
Requires-Dist: urllib3 (<2)
Project-URL: Documentation, https://github.com/cloudblue/connect-reports-runner
Project-URL: Repository, https://github.com/cloudblue/connect-reports-runner
